CHANGELOG.md
MANIFEST.in
README.md
requirements.txt
setup.py
keras_radam/__init__.py
keras_radam/backend.py
keras_radam/optimizer_v2.py
keras_rectified_adam.egg-info/PKG-INFO
keras_rectified_adam.egg-info/SOURCES.txt
keras_rectified_adam.egg-info/dependency_links.txt
keras_rectified_adam.egg-info/requires.txt
keras_rectified_adam.egg-info/top_level.txt
tests/__init__.py
tests/official.py
tests/test_optimizers.py
tests/test_similar.py