Metadata-Version: 2.1
Name: keras-rectified-adam
Version: 0.18.0
Summary: RAdam implemented in Keras & TensorFlow
Home-page: https://github.com/CyberZHG/keras-radam
Author: CyberZHG
Author-email: CyberZHG@users.noreply.github.com
License: MIT
Platform: UNKNOWN
Classifier: Programming Language :: Python :: 3.6
Classifier: License :: OSI Approved :: MIT License
Classifier: Operating System :: OS Independent
